pymyers/__init__.py
pymyers/debug.py
pymyers/myers.py
pymyers-0.2.1.dist-info/LICENSE
pymyers-0.2.1.dist-info/METADATA
pymyers-0.2.1.dist-info/WHEEL
pymyers-0.2.1.dist-info/top_level.txt
pymyers-0.2.1.dist-info/RECORD
