Metadata-Version: 2.1
Name: pymyers
Version: 0.2.1
Summary: Myers Diff with realtime and plot support
Author-email: Leo Wong <lei.wang6105@gmail.com>
Project-URL: Homepage, https://github.com/leowooong/PyMyers.git
Classifier: Programming Language :: Python :: 3
Classifier: License :: OSI Approved :: MIT License
Classifier: Operating System :: OS Independent
Requires-Python: >=3.7
License-File: LICENSE
